pandoc_jinja.py
pandoc_jinja-0.2.4.dist-info/LICENSE
pandoc_jinja-0.2.4.dist-info/METADATA
pandoc_jinja-0.2.4.dist-info/WHEEL
pandoc_jinja-0.2.4.dist-info/entry_points.txt
pandoc_jinja-0.2.4.dist-info/top_level.txt
pandoc_jinja-0.2.4.dist-info/RECORD
