Metadata-Version: 2.1
Name: pandoc-jinja
Version: 0.2.4
Summary: Render pandoc metadata variables inside the document
Author-email: Damien Clochard <damien.clochard@dalibo.com>
Project-URL: Homepage, https://github.com/daamien/pandoc-jinja
Project-URL: Bug Tracker, https://github.com/daamien/pandoc-jinja/issues
Classifier: Programming Language :: Python :: 3
Classifier: License :: OSI Approved :: MIT License
Classifier: Operating System :: OS Independent
Requires-Python: >=3.7
License-File: LICENSE
Requires-Dist: panflute
Requires-Dist: jinja2
